source_google_ads/__init__.py
source_google_ads/components.py
source_google_ads/config_migrations.py
source_google_ads/google_ads.py
source_google_ads/manifest.yaml
source_google_ads/models.py
source_google_ads/run.py
source_google_ads/schemas/customer_client.json
source_google_ads/schemas/service_accounts.json
source_google_ads/source.py
source_google_ads/spec.json
source_google_ads/streams.py
source_google_ads/utils.py
airbyte_source_google_ads-4.1.4.dist-info/METADATA
airbyte_source_google_ads-4.1.4.dist-info/WHEEL
airbyte_source_google_ads-4.1.4.dist-info/entry_points.txt
airbyte_source_google_ads-4.1.4.dist-info/RECORD
