Metadata-Version: 2.1
Name: airbyte-source-google-ads
Version: 4.1.4
Summary: Source implementation for Google Ads.
Home-page: https://airbyte.com
License: Elv2
Author: Airbyte
Author-email: contact@airbyte.io
Requires-Python: >=3.10,<3.12
Classifier: License :: Other/Proprietary License
Classifier: Programming Language :: Python :: 3
Classifier: Programming Language :: Python :: 3.10
Classifier: Programming Language :: Python :: 3.11
Requires-Dist: airbyte-cdk (>=7.5.1.post3.dev19705070276,<8.0.0)
Requires-Dist: google-ads (==27.0.0)
Requires-Dist: pendulum (<3.0.0)
Requires-Dist: protobuf (==4.25.2)
Project-URL: Documentation, https://docs.airbyte.com/integrations/sources/google-ads
Project-URL: Repository, https://github.com/airbytehq/airbyte
